{
  "to be": ["быть"],
  "that": ["тот"],
  "a question": ["вопрос"],
  "whether": ["будь то"],
  "noble": ["благородный"],
  "a mind": ["ум", "разум"],
  "to suffer": ["страдать", "терпеть"],
  "a sling": ["праща"],
  "an arrow": ["стрела"],
  "outrageous": ["неистовый", "возмутительный"],
  "fortune": ["судьба", "рок"],
  "to take": ["брать"],
  "an arms": ["оружие"],
  "against": ["против"],
  "a sea": ["море"],
  "a trouble": ["проблема"],
  "opposing": ["сопротивление"],
  "end": ["конец"],
  "them": ["их"],
  "to die": ["умереть"],
  "to sleep": ["спать"],
  "no more": ["не больше"],
  "to say": ["сказать"],
  "heartache": ["болезнь сердца"],
  "thousand": ["тысяча"],
  "natural": ["естественный"],
  "shock": ["потрясение"],
  "flesh": ["плоть"],
  "heir": ["наледовать"],
  "consummation": ["завершение"],
  "devoutly": ["искренне"],
  "perchance": ["может быть"],
  "dream": ["сновидения"],
  "rub": ["трение"],
  "death": ["смерть"],
  "may": ["мочь"],
  "shuffled off": ["сбрасывать"],
  "mortal coil": ["бренный мир"],
  "pause": ["пауза", "перерыв"],
  "respect": ["уважение"],
  "calamity": ["бедствие"],
  "long": ["долго", "долгий срок"],
  "life": ["жизнь"]
}